sharkreduce/__init__.py
sharkreduce/__main__.py
sharkreduce/activity.py
sharkreduce/device.py
sharkreduce/flow.py
sharkreduce/packet.py
sharkreduce-0.2.0.dist-info/METADATA
sharkreduce-0.2.0.dist-info/WHEEL
sharkreduce-0.2.0.dist-info/top_level.txt
sharkreduce-0.2.0.dist-info/RECORD
