Metadata-Version: 2.1
Name: sharkreduce
Version: 0.2.0
Summary: Convenience functionality to annotate and reduce wireshark captures.
Home-page: UNKNOWN
Author: Johannes Abel, Joseph Birkner, Tom Mirwald
License: BSD-3 Clause
Platform: UNKNOWN
Classifier: Programming Language :: Python :: 3
Classifier: Operating System :: OS Independent
Classifier: License :: OSI Approved :: BSD License
Requires-Python: >=3.6
Requires-Dist: pyyaml
Requires-Dist: progress
